amdf/__init__.py
amdf/core/__init__.py
amdf/core/config.py
amdf/core/exceptions.py
amdf/core/models.py
amdf/core/utils.py
amdf/core/logic/__init__.py
amdf/core/logic/blueprint.py
amdf/core/logic/generator.py
amdf/interfaces/__init__.py
amdf/interfaces/cli/__init__.py
amdf/interfaces/cli/guided.py
amdf/interfaces/cli/main.py
amdf/interfaces/cli/commands/__init__.py
amdf/interfaces/mcp/__init__.py
amdf/interfaces/mcp/server.py
amdf-1.0.2.dist-info/licenses/LICENSE
amdf-1.0.2.dist-info/METADATA
amdf-1.0.2.dist-info/WHEEL
amdf-1.0.2.dist-info/entry_points.txt
amdf-1.0.2.dist-info/top_level.txt
amdf-1.0.2.dist-info/RECORD
