Metadata-Version: 2.4
Name: amdf
Version: 1.0.2
Summary: Transform Kubernetes CRDs into type-safe KCL schemas and developer-friendly blueprints
Author: AMDF Team
Maintainer: AMDF Team
License:                                  Apache License
Project-URL: Documentation, https://amdf.readthedocs.io/en/latest/
Project-URL: Repository, https://github.com/segoja7/agnostic-multicloud-delivery-framework
Keywords: kubernetes,crossplane,kcl,infrastructure-as-code,crd,schema-generation,mcp,platform-engineering
Requires-Python: >=3.10
License-File: LICENSE
Requires-Dist: mcp>=1.0.0
Requires-Dist: pydantic>=2.0.0
Requires-Dist: pydantic-settings>=2.0.0
Requires-Dist: pyyaml>=6.0
Requires-Dist: click>=8.0.0
Requires-Dist: rich>=13.0.0
Requires-Dist: typer>=0.9.0
Requires-Dist: ollama>=0.6.0
Provides-Extra: dev
Requires-Dist: pytest; extra == "dev"
Requires-Dist: black; extra == "dev"
Requires-Dist: flake8; extra == "dev"
Requires-Dist: mypy; extra == "dev"
Requires-Dist: pre-commit; extra == "dev"
Provides-Extra: docs
Requires-Dist: mkdocs; extra == "docs"
Requires-Dist: mkdocs-material; extra == "docs"
Requires-Dist: mkdocs-mermaid2-plugin; extra == "docs"
Dynamic: license-file
